{"cameraMode":{"drawMode":0,"name":"Shaded","section":"Shading Mode"},"sceneLighting":false,"audioPlay":false,"sceneViewState":{"m_AlwaysRefresh":false,"showFog":true,"showSkybox":false,"showFlares":true,"showImageEffects":true,"showParticleSystems":true,"showVisualEffectGraphs":true,"m_FxEnabled":true},"in2DMode":false,"pivot":{"x":0.0,"y":1.0587871074676514,"z":0.0},"rotation":{"x":0.21135129034519196,"y":-0.47489914298057558,"z":0.11864212155342102,"w":0.846018373966217},"size":15.674574851989746,"orthographic":false}